objectstash/__init__.py
objectstash/fs_adapter.py
objectstash/objectstash.py
objectstash/s3_adapter.py
objectstash/storage_adapter.py
objectstash-0.1.2.dist-info/WHEEL
objectstash-0.1.2.dist-info/METADATA
objectstash-0.1.2.dist-info/RECORD
