Metadata-Version: 2.1
Name: objectstash
Version: 0.1.2
Summary: A wrapper around object stores.
Home-page: https://github.com/ludwigschmidt/objectstash
License: MIT
Author: Ludwig Schmidt
Author-email: ludwigschmidt2@gmail.com
Requires-Python: >=3.7,<4.0
Classifier: License :: OSI Approved :: MIT License
Classifier: Programming Language :: Python :: 3
Classifier: Programming Language :: Python :: 3.7
Classifier: Programming Language :: Python :: 3.8
Requires-Dist: boto3 (>=1.14.38,<2.0.0)
Requires-Dist: loguru (>=0.5.2,<0.6.0)
Project-URL: Repository, https://github.com/ludwigschmidt/objectstash
